mglyph/__init__.py
mglyph/canvas.py
mglyph/colormap.py
mglyph/constants.py
mglyph/convert.py
mglyph/mglyph.py
mglyph/transform.py
mglyph-0.5.5.dist-info/licenses/LICENSE
mglyph-0.5.5.dist-info/METADATA
mglyph-0.5.5.dist-info/WHEEL
mglyph-0.5.5.dist-info/top_level.txt
mglyph-0.5.5.dist-info/RECORD
