Metadata-Version: 2.4
Name: mglyph
Version: 0.5.5
Summary: The Malleable Glyph package
Home-page: https://github.com/adamherout/mglyph
Author: Adam Herout, Vojtech Bartl
Author-email: herout@vutbr.cz, ibartl@fit.vut.cz
License: MIT
Classifier: Development Status :: 3 - Alpha
Classifier: Programming Language :: Python :: 3
Requires-Python: >=3.7
License-File: LICENSE
Requires-Dist: skia-python
Requires-Dist: colour
Requires-Dist: numpy
Requires-Dist: matplotlib
Requires-Dist: qoi
Dynamic: author
Dynamic: author-email
Dynamic: classifier
Dynamic: description
Dynamic: description-content-type
Dynamic: home-page
Dynamic: license
Dynamic: license-file
Dynamic: requires-dist
Dynamic: requires-python
Dynamic: summary
